pykeyvi.so
pykeyvi-0.2.4.dist-info/DESCRIPTION.rst
pykeyvi-0.2.4.dist-info/METADATA
pykeyvi-0.2.4.dist-info/RECORD
pykeyvi-0.2.4.dist-info/WHEEL
pykeyvi-0.2.4.dist-info/metadata.json
pykeyvi-0.2.4.dist-info/top_level.txt
.libspykeyvi/libboost_filesystem-d4710d70.so.1.60.0
.libspykeyvi/libboost_system-17a2ee5a.so.1.60.0
.libspykeyvi/libboost_iostreams-c8cf1a19.so.1.60.0
.libspykeyvi/libbz2-7225278b.so.1.0.3
.libspykeyvi/libboost_regex-40847e79.so.1.60.0
.libspykeyvi/libz-a147dcb0.so.1.2.3
.libspykeyvi/libsnappy-42eb71d0.so.1.1.3
.libspykeyvi/libboost_program_options-c4c97887.so.1.60.0
.libspykeyvi/libboost_thread-60ad122d.so.1.60.0
keyvicli/cli.py
keyvicli/__init__.py
pykeyvi-0.2.4.data/scripts/keyvi
