Metadata-Version: 1.1
Name: pykeyvi
Version: 0.2.4
Summary: Python package for keyvi
Home-page: https://github.com/cliqz-oss/keyvi
Author: Hendrik Muhs
Author-email: hendrik.muhs@gmail.com
License: ASL 2.0
Download-URL: https://github.com/cliqz-oss/keyvi/tarball/v0.2.4
Keywords: FST
Platform: UNKNOWN
Classifier: Programming Language :: C++
Classifier: Programming Language :: Cython
Classifier: Programming Language :: Python
Classifier: Programming Language :: Python :: 2.7
Classifier: Programming Language :: Python :: 3.4
Classifier: Programming Language :: Python :: 3.5
Classifier: Programming Language :: Python :: Implementation :: CPython
Classifier: Programming Language :: Python :: Implementation :: PyPy
Classifier: Operating System :: MacOS :: MacOS X
Classifier: Operating System :: Unix
